airc/__init__.py
airc/abstracts.py
airc/bot.py
airc/client.py
airc/enums.py
airc/errors.py
airc/events.py
airc/server.py
airc/utils.py
airc-0.0.2.dist-info/LICENSE.txt
airc-0.0.2.dist-info/METADATA
airc-0.0.2.dist-info/WHEEL
airc-0.0.2.dist-info/top_level.txt
airc-0.0.2.dist-info/RECORD
