Metadata-Version: 2.1
Name: airc
Version: 0.0.2
Summary: An asynchronous IRC implementation
Home-page: https://github.com/CraftSpider/AIRC
Author: CraftSpider
Author-email: runetynan@gmail.com
License: MIT
Project-URL: Source, https://github.com/CraftSpider/AIRC
Project-URL: Tracker, https://github.com/CraftSpider/AIRC/issues
Keywords: irc asyncio
Platform: UNKNOWN
Classifier: Development Status :: 3 - Alpha
Classifier: Intended Audience :: Developers
Classifier: Topic :: Communications :: Chat :: Internet Relay Chat
Classifier: License :: OSI Approved :: MIT License
Classifier: Programming Language :: Python :: 3.5
Requires-Python: >=3.5
